annotell_export-0.2.1-py3.8-nspkg.pth
annotell/export/__init__.py
annotell/export/export_api_client.py
annotell_export-0.2.1.dist-info/METADATA
annotell_export-0.2.1.dist-info/WHEEL
annotell_export-0.2.1.dist-info/namespace_packages.txt
annotell_export-0.2.1.dist-info/top_level.txt
annotell_export-0.2.1.dist-info/RECORD
