Metadata-Version: 2.1
Name: annotell-export
Version: 0.2.1
Summary: Annotell Export API Client
Home-page: https://github.com/annotell/annotell-python
Download-URL: https://github.com/annotell/annotell-python/tarball/0.2.1
Author: Annotell
Author-email: Michel Edkrantz <michel.edkrantz@annotell.com>
License: MIT
Keywords: API,Annotell
Classifier: Development Status :: 3 - Alpha
Classifier: License :: OSI Approved :: MIT License
Classifier: Intended Audience :: Developers
Classifier: Programming Language :: Python :: 3
Requires-Python: ~=3.6
Requires-Dist: annotell-auth (<3,>=2.0.1)
Requires-Dist: requests (<3,>=2.23.0)
